{
  "Chapter 09": [
    {
      "code": "0901.21.000",
      "hs6": "0901.21",
      "category": "飲料（コーヒー）",
      "description": "焙煎コーヒー（カフェイン除去なし）=0901.21。カフェイン除去済み=0901.22。生豆=0901.11。"
    },
    {
      "code": "0902.10.900",
      "hs6": "0902.10",
      "category": "飲料（茶）",
      "description": "緑茶（3kg以下の包装）=0902.10。JP: 粉末状=0902.10-100、その他=0902.10-900。紅茶=0902.30/40。"
    }
  ],
  "Chapter 18": [
    {
      "code": "1806.31.000",
      "hs6": "1806.31",
      "category": "食品（チョコレート）",
      "description": "チョコレート菓子（詰物をしたもの）=1806.31。詰物なし=1806.32。その他チョコレート製品=1806.90。"
    }
  ],
  "Chapter 21": [
    {
      "code": "2106.90.300",
      "hs6": "2106.90",
      "category": "栄養補助食品",
      "description": "調製食料品（その他）=2106.90。JP: ビタミン・ミネラル・アミノ酸等をもととした栄養補助食品=2106.90-300。豆腐=2106.90-200。"
    }
  ],
  "Chapter 30": [
    {
      "code": "3004.90.000",
      "hs6": "3004.90",
      "category": "医薬品・サプリメント",
      "description": "投与量にしたもの又は小売用の形状にした医薬品=3004.90。ビタミン剤=2106.90（食品扱い）の場合あり。JP: 3004.90-000。"
    }
  ],
  "Chapter 33": [
    {
      "code": "3304.10.000",
      "hs6": "3304.10",
      "category": "化粧品",
      "description": "唇のメーキャップ用調製品=3304.10。眼のメーキャップ=3304.20。パウダー=3304.91。マニキュア=3304.30。"
    },
    {
      "code": "3303.00.000",
      "hs6": "3303.00",
      "category": "香水・フレグランス",
      "description": "香水類及びオーデコロン類=3303.00。JP: 3303.00-000。"
    },
    {
      "code": "3304.99.900",
      "hs6": "3304.99",
      "category": "スキンケア製品",
      "description": "皮膚の手入れ用調製品（その他）=3304.99。JP: 化粧下=3304.99-100、クリーム=3304.99-200、その他=3304.99-900。"
    },
    {
      "code": "3305.10.000",
      "hs6": "3305.10",
      "category": "ヘアケア製品",
      "description": "シャンプー=3305.10。ヘアラッカー=3305.30。その他の頭髪用調製品=3305.90。"
    }
  ],
  "Chapter 34": [
    {
      "code": "3401.30.000",
      "hs6": "3401.30",
      "category": "石鹸・洗浄剤",
      "description": "有機界面活性剤及びその調製品（皮膚の洗浄に使用する液状・クリーム状のもの）=3401.30。固形石鹸（化粧用）=3401.11。"
    },
    {
      "code": "3406.00.000",
      "hs6": "3406.00",
      "category": "ろうそく・キャンドル",
      "description": "ろうそく及びこれに類する物品=3406.00。"
    }
  ],
  "Chapter 39": [
    {
      "code": "3924.10.000",
      "hs6": "3924.10",
      "category": "プラスチック製品",
      "description": "プラスチック製の食卓用品及び台所用品=3924.10。その他の家庭用品=3924.90。"
    }
  ],
  "Chapter 42": [
    {
      "code": "4202.21.000",
      "hs6": "4202.21",
      "category": "バッグ・鞄",
      "description": "ハンドバッグ類。外面が革製=4202.21、プラスチックシート製又は紡織用繊維製=4202.22。JP: 4202.21-000(外面が革製又はコンポジションレザー製)。"
    },
    {
      "code": "4202.31.000",
      "hs6": "4202.31",
      "category": "革小物",
      "description": "ポケット又はハンドバッグに携帯する製品。革製=4202.31、プラスチック・繊維製=4202.32。"
    },
    {
      "code": "4202.92.000",
      "hs6": "4202.92",
      "category": "バッグ（リュック）",
      "description": "外面がプラスチックシート製又は紡織用繊維製のバッグ類=4202.92。JP: 4202.92-000。"
    },
    {
      "code": "4202.12.000",
      "hs6": "4202.12",
      "category": "旅行用鞄",
      "description": "トランク・スーツケース類。外面がプラスチック又は紡織用繊維製=4202.12、革製=4202.11。"
    },
    {
      "code": "4202.99.000",
      "hs6": "4202.99",
      "category": "ケース・カバー",
      "description": "携帯電話ケース等の容器。その他の材料=4202.99。革製=4202.91、プラスチック・繊維製=4202.92。"
    }
  ],
  "Chapter 44": [
    {
      "code": "4419.19.090",
      "hs6": "4419.19",
      "category": "木製品",
      "description": "木製の食卓用品及び台所用品=4419。竹製まな板=4419.11。JP: 漆塗り=4419.19-010、その他=4419.19-090。"
    }
  ],
  "Chapter 48": [
    {
      "code": "4820.10.000",
      "hs6": "4820.10",
      "category": "紙製品",
      "description": "帳簿、会計簿、雑記帳、注文帳、便せん、メモ帳等=4820.10。練習帳=4820.20。バインダー=4820.30。"
    }
  ],
  "Chapter 49": [
    {
      "code": "4901.99.000",
      "hs6": "4901.99",
      "category": "書籍・印刷物",
      "description": "印刷された書籍（その他）=4901.99。辞典・事典=4901.91。単一シート=4901.10。"
    }
  ],
  "Chapter 57": [
    {
      "code": "5703.30.000",
      "hs6": "5703.30",
      "category": "じゅうたん・床敷物",
      "description": "タフテッドじゅうたん・床用敷物（ナイロン製）=5703.20、その他合成繊維=5703.30。手織り=5701、結びパイル=5701.10。JP: 5703.30-000。"
    }
  ],
  "Chapter 61": [
    {
      "code": "6109.10.900",
      "hs6": "6109.10",
      "category": "衣料品（ニット）",
      "description": "綿製Tシャツ・シングレット類。HTS 6109.10.00 stat.12(男子用綿製)。JP: 6109.10-900(その他のもの)。合成繊維製は6109.90。"
    },
    {
      "code": "6110.20.000",
      "hs6": "6110.20",
      "category": "衣料品（ニットウェア）",
      "description": "ジャージー、プルオーバー、カーディガン等（メリヤス編み）。綿製=6110.20、羊毛製=6110.11、合成繊維製=6110.30。"
    },
    {
      "code": "6108.21.000",
      "hs6": "6108.21",
      "category": "衣料品（下着）",
      "description": "女子用ブリーフ・パンティ（メリヤス編み）。綿製=6108.21、人造繊維製=6108.22。男子用は6107。"
    },
    {
      "code": "6115.95.000",
      "hs6": "6115.95",
      "category": "衣料品（靴下類）",
      "description": "靴下類（メリヤス編み）。綿製=6115.95、合成繊維製=6115.96。パンティストッキング=6115.21/22。"
    },
    {
      "code": "6112.41.000",
      "hs6": "6112.41",
      "category": "衣料品（水着）",
      "description": "女子用水着（メリヤス編み）。合成繊維製=6112.41。男子用=6112.31。トラックスーツ=6112.11/12。"
    }
  ],
  "Chapter 62": [
    {
      "code": "6205.20.000",
      "hs6": "6205.20",
      "category": "衣料品（織物）",
      "description": "男子用シャツ（織物製）。綿製=6205.20、人造繊維製=6205.30。JP: 6205.20-000。"
    },
    {
      "code": "6201.40.000",
      "hs6": "6201.40",
      "category": "衣料品（アウター）",
      "description": "男子用オーバーコート・アノラック類（織物製）。人造繊維製=6201.40、綿製=6201.30、羊毛製=6201.20。"
    },
    {
      "code": "6204.43.000",
      "hs6": "6204.43",
      "category": "衣料品（婦人）",
      "description": "女子用ドレス（織物製）。合成繊維製=6204.43、綿製=6204.42。スーツ=6204.11-19、スカート=6204.51-59。"
    },
    {
      "code": "6203.42.000",
      "hs6": "6203.42",
      "category": "衣料品（ボトムス）",
      "description": "男子用ズボン・ショーツ（織物製）。綿製=6203.42、合成繊維製=6203.43。女子用=6204.62/63。"
    },
    {
      "code": "6204.52.000",
      "hs6": "6204.52",
      "category": "衣料品（婦人ボトムス）",
      "description": "女子用スカート（織物製）。綿製=6204.52、合成繊維製=6204.53。"
    }
  ],
  "Chapter 63": [
    {
      "code": "6302.60.000",
      "hs6": "6302.60",
      "category": "繊維製品（タオル）",
      "description": "トイレットリネン及びキッチンリネン（テリータオル地、綿製）=6302.60。"
    },
    {
      "code": "6301.40.000",
      "hs6": "6301.40",
      "category": "繊維製品（毛布）",
      "description": "合成繊維製の毛布=6301.40。綿製=6301.30。羊毛製=6301.20。"
    }
  ],
  "Chapter 64": [
    {
      "code": "6404.11.000",
      "hs6": "6404.11",
      "category": "履物",
      "description": "本底がゴム製又はプラスチック製、甲が紡織用繊維のスポーツ用履物=6404.11。JP: スポーツ用の履物及びテニスシューズ等。その他=6404.19。"
    },
    {
      "code": "6403.59.000",
      "hs6": "6403.59",
      "category": "履物（革）",
      "description": "本底がゴム・プラスチック製、甲が革製の靴=6403.59(くるぶしを覆わないもの)。くるぶしを覆うもの=6403.51/91。"
    }
  ],
  "Chapter 65": [
    {
      "code": "6505.00.000",
      "hs6": "6505.00",
      "category": "帽子類",
      "description": "メリヤス編み又はクロセ編みの帽子、ヘアネット等=6505.00。フェルト帽子=6505に含む。"
    }
  ],
  "Chapter 66": [
    {
      "code": "6601.99.000",
      "hs6": "6601.99",
      "category": "傘",
      "description": "傘（その他）=6601.99。折畳み式=6601.91。ビーチパラソル=6601.10。"
    }
  ],
  "Chapter 69": [
    {
      "code": "6912.00.000",
      "hs6": "6912.00",
      "category": "陶磁器",
      "description": "陶磁製の食卓用品、台所用品等（磁器製を除く）=6912.00。磁器製=6911.10。"
    }
  ],
  "Chapter 71": [
    {
      "code": "7117.19.000",
      "hs6": "7117.19",
      "category": "宝飾品・アクセサリー",
      "description": "身辺用模造細貨類（卑金属製）=7117.19。カフスボタン=7117.11。貴金属製の身辺用細貨類は7113。"
    }
  ],
  "Chapter 73": [
    {
      "code": "7323.93.000",
      "hs6": "7323.93",
      "category": "金属製容器",
      "description": "ステンレス鋼製の食卓用品、台所用品等=7323.93。鋳鉄製=7323.91/92。"
    }
  ],
  "Chapter 82": [
    {
      "code": "8211.91.000",
      "hs6": "8211.91",
      "category": "工具・刃物",
      "description": "テーブルナイフ（固定刃）=8211.91。その他のナイフ（固定刃）=8211.92。折り畳みナイフ=8211.93。詰合せセット=8211.10。"
    }
  ],
  "Chapter 84": [
    {
      "code": "8471.30.000",
      "hs6": "8471.30",
      "category": "電子機器（PC）",
      "description": "携帯用自動データ処理機械（10kg以下、CPU・キーボード・ディスプレイ内蔵）=8471.30。HTS 8471.30.01 stat.00。"
    },
    {
      "code": "8471.30.000",
      "hs6": "8471.30",
      "category": "電子機器（タブレット）",
      "description": "タブレット端末は携帯用自動データ処理機械として8471.30。デスクトップPC=8471.41/49。"
    }
  ],
  "Chapter 85": [
    {
      "code": "8517.13.000",
      "hs6": "8517.13",
      "category": "電子機器（通信）",
      "description": "スマートフォン=8517.13。HTS 8517.13.00 stat.00。JP: 8517.13-000(スマートフォン)。その他の携帯電話=8517.14。"
    },
    {
      "code": "8518.30.900",
      "hs6": "8518.30",
      "category": "電子機器（音響）",
      "description": "ヘッドホン・イヤホン=8518.30。HTS 8518.30.20 stat.00。JP: 8518.30-100(ヘッドホン)、8518.30-900(その他=イヤホン等)。"
    },
    {
      "code": "8525.81.000",
      "hs6": "8525.81",
      "category": "電子機器（光学）",
      "description": "テレビジョンカメラ、デジタルカメラ、ビデオカメラレコーダー=8525.81。"
    },
    {
      "code": "8504.40.900",
      "hs6": "8504.40",
      "category": "電子機器（電源）",
      "description": "スタティックコンバーター=8504.40。HTS: 8504.40.85(通信機器用)。ADP機器用電源=8504.40.60/70。JP: 8504.40-900(その他)。"
    },
    {
      "code": "8507.60.000",
      "hs6": "8507.60",
      "category": "電子機器（蓄電池）",
      "description": "リチウムイオン蓄電池=8507.60。HTS 8507.60.00 stat.90(一般消費者向け)。EV用=stat.10。ニッケル水素=8507.50。"
    },
    {
      "code": "8518.22.000",
      "hs6": "8518.22",
      "category": "電子機器（音響）",
      "description": "複数型拡声器（同一エンクロージャー）=8518.22。単一型=8518.21。JP: 8518.22-000。"
    }
  ],
  "Chapter 87": [
    {
      "code": "8708.99.900",
      "hs6": "8708.99",
      "category": "自動車部品",
      "description": "自動車部品（その他）=8708.99。JP: 車輪式トラクター用=8708.99-100、その他=8708.99-900。バンパー=8708.10、ブレーキ=8708.30。"
    }
  ],
  "Chapter 88": [
    {
      "code": "8806.10.000",
      "hs6": "8806.10",
      "category": "無人航空機（ドローン）",
      "description": "無人航空機=8806.10（最大離陸重量250g以下）。250g超2kg以下=8806.21。2kg超25kg以下=8806.22。25kg超150kg以下=8806.23。150kg超=8806.24。JP: 8806.10-000。"
    }
  ],
  "Chapter 90": [
    {
      "code": "9004.10.000",
      "hs6": "9004.10",
      "category": "光学機器（眼鏡）",
      "description": "サングラス=9004.10。その他の眼鏡（矯正用等）=9004.90。"
    }
  ],
  "Chapter 91": [
    {
      "code": "9102.12.000",
      "hs6": "9102.12",
      "category": "時計",
      "description": "電子式腕時計。オプトエレクトロニクス表示部のみ=9102.12(デジタル/スマートウォッチ)、機械式表示部のみ=9102.11(アナログ)。非電子式=9102.21/29。"
    }
  ],
  "Chapter 92": [
    {
      "code": "9202.90.000",
      "hs6": "9202.90",
      "category": "弦楽器",
      "description": "その他の弦楽器=9202.90。ギター=9202.90。JP: 9202.90-000。バイオリン=9202.10。"
    },
    {
      "code": "9201.10.000",
      "hs6": "9201.10",
      "category": "鍵盤楽器",
      "description": "アップライトピアノ=9201.10。グランドピアノ=9201.20。電子ピアノ・キーボード=9207。JP: 9201.10-000。"
    },
    {
      "code": "9206.00.000",
      "hs6": "9206.00",
      "category": "打楽器",
      "description": "打楽器=9206.00。ドラムセット、シンバル等。JP: 9206.00-000。"
    },
    {
      "code": "9205.90.000",
      "hs6": "9205.90",
      "category": "管楽器・弦楽器",
      "description": "その他の管楽器=9205.90。トランペット=9205.10。フルート=9205.10。バイオリン=9202.10。チェロ=9202.10。JP: 9205.90-000。"
    }
  ],
  "Chapter 94": [
    {
      "code": "9401.61.000",
      "hs6": "9401.61",
      "category": "家具（座るもの）",
      "description": "木製フレーム・アップホルスターの腰掛け=9401.61。金属フレーム=9401.71。JP: 9401.61-000。"
    },
    {
      "code": "9403.60.000",
      "hs6": "9403.60",
      "category": "家具（テーブル）",
      "description": "その他の木製家具=9403.60(テーブル・デスク含む)。事務所用木製家具=9403.30、寝室用=9403.50。"
    },
    {
      "code": "9404.21.000",
      "hs6": "9404.21",
      "category": "家具（寝具）",
      "description": "マットレス（セルラーラバー製又は多泡性プラスチック製）=9404.21。その他材料製=9404.29。布団・ベッドスプレッド=9404.40。"
    },
    {
      "code": "9405.11.000",
      "hs6": "9405.11",
      "category": "照明器具",
      "description": "LED光源用天井・壁掛け照明器具=9405.11。卓上・床置き=9405.21/29。非電気式=9405.50。"
    }
  ],
  "Chapter 95": [
    {
      "code": "9503.00.000",
      "hs6": "9503.00",
      "category": "玩具",
      "description": "三輪車、人形、その他の玩具、縮尺模型及びパズル=9503.00。JP: 9503.00-000。"
    },
    {
      "code": "9506.91.000",
      "hs6": "9506.91",
      "category": "スポーツ用品",
      "description": "身体トレーニング用具、体操用具及び競技用具=9506.91。ゴルフクラブ=9506.31、テニスラケット=9506.51。"
    }
  ],
  "Chapter 96": [
    {
      "code": "9603.21.000",
      "hs6": "9603.21",
      "category": "ブラシ類",
      "description": "歯ブラシ（義歯用ブラシを含む）=9603.21。HTS: 2¢ each + Free(特恵)。その他の身体用ブラシ=9603.29。"
    },
    {
      "code": "9608.10.900",
      "hs6": "9608.10",
      "category": "筆記具",
      "description": "ボールペン=9608.10。JP: 油性=9608.10-100、その他=9608.10-900。フェルトペン=9608.20。万年筆=9608.30。シャープペンシル=9608.40。"
    }
  ],
  "Chapter 97": [
    {
      "code": "9701.10.000",
      "hs6": "9701.10",
      "category": "美術品・収集品",
      "description": "絵画（手描き）=9701.10。版画=9702。彫刻=9703。収集品=9705。骨とう=9706。JP: 9701.10-000。"
    }
  ]
}